cachecall/__init__.py
cachecall/cache.py
cachecall/cache_keys.py
cachecall/data.py
cachecall/decorators.py
cachecall/expire_time.py
cachecall/units.py
tests/__init__.py
tests/conftest.py
tests/test_cache_async_functions.py
tests/test_cache_group.py
tests/test_cache_max_mem_size.py
tests/test_cache_obj.py
tests/test_cache_sync_functions.py
tests/test_expire_time.py
tests/test_expire_time_with_decorator.py
tests/test_ttl.py
tests/test_units.py
tests/fixtures/__init__.py
tests/fixtures/data.py
cachecall-0.1.0.dist-info/METADATA
cachecall-0.1.0.dist-info/WHEEL
cachecall-0.1.0.dist-info/top_level.txt
cachecall-0.1.0.dist-info/RECORD
