Metadata-Version: 2.1
Name: cachecall
Version: 0.1.0
Summary: A cache library for sync and async functions with ttl and expiration time.
Home-page: https://github.com/igor-rodrigues-ss/cachecall
Author: Igor Rodrigues Sousa Silva
Author-email: igor.rodrigues.ss98@gmail.com
License: MIT
Keywords: cache caching cachecall cached cache-memory
Platform: UNKNOWN
Classifier: Development Status :: 3 - Alpha
Classifier: Intended Audience :: Developers
Classifier: Topic :: Software Development :: Build Tools
Classifier: License :: OSI Approved :: MIT License
Classifier: Programming Language :: Python :: 3.7
Classifier: Programming Language :: Python :: 3.8
Classifier: Programming Language :: Python :: 3.9
Classifier: Programming Language :: Python :: 3.10
Requires-Python: >=3.7
